[
  {
    "href": "/nes/2853/",
    "src": "/media/images/200812282332047882.gif"
  },
  {
    "href": "/nes/1201/",
    "src": "/media/images/1203.jpg"
  },
  {
    "href": "/nes/7403/",
    "src": "/media/images/2010124105420780.jpg"
  },
  {
    "href": "/nes/2928/",
    "src": "/media/images/200906171300406090.gif"
  },
  {
    "href": "/nes/3282/",
    "src": "/media/images/20101611235647.jpg"
  },
  {
    "href": "/nes/7383/",
    "src": "/media/images/201012410545228.gif"
  },
  {
    "href": "/nes/3285/",
    "src": "/media/images/20101611244970.jpg"
  },
  {
    "href": "/nes/7396/",
    "src": "/media/images/2010124105415618.jpg"
  },
  {
    "href": "/nes/1677/",
    "src": "/media/images/1680.jpg"
  },
  {
    "href": "/nes/60/",
    "src": "/media/images/60.jpg"
  },
  {
    "href": "/nes/2285/",
    "src": "/media/images/2292.jpg"
  },
  {
    "href": "/nes/3289/",
    "src": "/media/images/20101611253482.jpg"
  },
  {
    "href": "/nes/7402/",
    "src": "/media/images/2010124105419262.jpg"
  },
  {
    "href": "/nes/3904/",
    "src": "/media/images/20101685831810.jpg"
  },
  {
    "href": "/nes/7408/",
    "src": "/media/images/2010124105424429.jpg"
  },
  {
    "href": "/nes/47/",
    "src": "/media/images/47.jpg"
  },
  {
    "href": "/nes/2305/",
    "src": "/media/images/200810181029048154.gif"
  },
  {
    "href": "/nes/7419/",
    "src": "/media/images/2010124105430380.jpg"
  },
  {
    "href": "/nes/7424/",
    "src": "/media/images/2010124105433470.jpg"
  },
  {
    "href": "/nes/7426/",
    "src": "/media/images/2010124105442223.jpg"
  },
  {
    "href": "/nes/3286/",
    "src": "/static/logo.png"
  },
  {
    "href": "/nes/3287/",
    "src": "/media/images/20101611249109.jpg"
  },
  {
    "href": "/nes/7409/",
    "src": "/media/images/2010124105424648.jpg"
  },
  {
    "href": "/nes/7425/",
    "src": "/media/images/2010124105442113.jpg"
  },
  {
    "href": "/nes/7414/",
    "src": "/media/images/2010124105427231.jpg"
  },
  {
    "href": "/nes/7382/",
    "src": "/media/images/201012410545567.gif"
  },
  {
    "href": "/nes/7386/",
    "src": "/media/images/201012410548657.jpg"
  },
  {
    "href": "/nes/2406/",
    "src": "/media/images/200810181101405496.gif"
  },
  {
    "href": "/nes/3301/",
    "src": "/media/images/20101611335742.jpg"
  },
  {
    "href": "/nes/3306/",
    "src": "/media/images/20101611353764.jpg"
  },
  {
    "href": "/nes/3302/",
    "src": "/media/images/20101611343955.jpg"
  },
  {
    "href": "/nes/3320/",
    "src": "/media/images/20101611514758.jpg"
  },
  {
    "href": "/nes/7428/",
    "src": "/media/images/2010124105443175.jpg"
  },
  {
    "href": "/nes/7415/",
    "src": "/media/images/2010124105428191.jpg"
  },
  {
    "href": "/nes/7397/",
    "src": "/media/images/2010124105415669.jpg"
  },
  {
    "href": "/nes/3281/",
    "src": "/media/images/20101611232210.jpg"
  },
  {
    "href": "/nes/3307/",
    "src": "/media/images/20101611358363.jpg"
  },
  {
    "href": "/nes/2306/",
    "src": "/media/images/200810181029055214.gif"
  },
  {
    "href": "/nes/2981/",
    "src": "/media/images/20101603144244.jpg"
  },
  {
    "href": "/nes/7421/",
    "src": "/media/images/2010124105431388.jpg"
  },
  {
    "href": "/nes/7399/",
    "src": "/media/images/2010124105416116.jpg"
  },
  {
    "href": "/nes/7407/",
    "src": "/media/images/2010124105423363.jpg"
  },
  {
    "href": "/nes/3319/",
    "src": "/media/images/20101611441657.png"
  },
  {
    "href": "/nes/7413/",
    "src": "/media/images/2010124105426894.jpg"
  },
  {
    "href": "/nes/3293/",
    "src": "/media/images/2010161136248.jpg"
  },
  {
    "href": "/nes/1533/",
    "src": "/media/images/1535.jpg"
  },
  {
    "href": "/nes/3284/",
    "src": "/media/images/20101611242464.jpg"
  },
  {
    "href": "/nes/3295/",
    "src": "/media/images/20101611312859.jpg"
  },
  {
    "href": "/nes/3304/",
    "src": "/media/images/20101611347688.jpg"
  },
  {
    "href": "/nes/7394/",
    "src": "/media/images/2010124105413419.jpg"
  },
  {
    "href": "/nes/2915/",
    "src": "/media/images/200906171255549911.gif"
  },
  {
    "href": "/nes/44/",
    "src": "/media/images/44.jpg"
  },
  {
    "href": "/nes/7404/",
    "src": "/media/images/2010124105420887.jpg"
  },
  {
    "href": "/nes/7384/",
    "src": "/static/logo.png"
  },
  {
    "href": "/nes/7435/",
    "src": "/media/images/2010124105449689.jpg"
  },
  {
    "href": "/nes/66/",
    "src": "/media/images/66.jpg"
  },
  {
    "href": "/nes/7412/",
    "src": "/media/images/2010124105426728.jpg"
  },
  {
    "href": "/nes/7431/",
    "src": "/media/images/2010124105446775.jpg"
  },
  {
    "href": "/nes/7416/",
    "src": "/media/images/2010124105428864.jpg"
  },
  {
    "href": "/nes/3272/",
    "src": "/media/images/20101611154667.jpg"
  },
  {
    "href": "/nes/7432/",
    "src": "/media/images/2010124105446882.jpg"
  },
  {
    "href": "/nes/2772/",
    "src": "/media/images/200811151145424204.gif"
  },
  {
    "href": "/nes/2914/",
    "src": "/media/images/200906171255514044.gif"
  },
  {
    "href": "/nes/2460/",
    "src": "/media/images/200810181249578874.gif"
  },
  {
    "href": "/nes/7417/",
    "src": "/media/images/2010124105428971.jpg"
  },
  {
    "href": "/nes/7385/",
    "src": "/static/logo.png"
  },
  {
    "href": "/nes/7389/",
    "src": "/media/images/2010124105410502.jpg"
  },
  {
    "href": "/nes/7392/",
    "src": "/media/images/2010124105412582.jpg"
  },
  {
    "href": "/nes/7439/",
    "src": "/media/images/2010124105452331.jpg"
  },
  {
    "href": "/nes/7411/",
    "src": "/media/images/2010124105426621.jpg"
  },
  {
    "href": "/nes/7401/",
    "src": "/media/images/2010124105418249.jpg"
  },
  {
    "href": "/nes/2847/",
    "src": "/media/images/200812282331497661.gif"
  },
  {
    "href": "/nes/7442/",
    "src": "/media/images/2010124105454186.jpg"
  },
  {
    "href": "/nes/7437/",
    "src": "/media/images/2010124105451993.jpg"
  },
  {
    "href": "/nes/3303/",
    "src": "/media/images/20101611345804.jpg"
  },
  {
    "href": "/nes/7420/",
    "src": "/media/images/2010124105430204.jpg"
  },
  {
    "href": "/nes/1683/",
    "src": "/media/images/1686.jpg"
  },
  {
    "href": "/nes/7441/",
    "src": "/media/images/2010124105453843.jpg"
  },
  {
    "href": "/nes/7440/",
    "src": "/media/images/2010124105453397.jpg"
  },
  {
    "href": "/nes/7429/",
    "src": "/media/images/2010124105444305.jpg"
  },
  {
    "href": "/nes/7388/",
    "src": "/media/images/201012410549828.jpg"
  },
  {
    "href": "/nes/3885/",
    "src": "/media/images/20101684752351.jpg"
  },
  {
    "href": "/nes/7400/",
    "src": "/media/images/2010124105417182.jpg"
  },
  {
    "href": "/nes/7405/",
    "src": "/media/images/2010124105422916.gif"
  },
  {
    "href": "/nes/7395/",
    "src": "/media/images/2010124105414378.jpg"
  },
  {
    "href": "/nes/3300/",
    "src": "/media/images/20101611332557.jpg"
  },
  {
    "href": "/nes/3296/",
    "src": "/media/images/20101611314714.jpg"
  },
  {
    "href": "/nes/3310/",
    "src": "/media/images/20101611410747.jpg"
  },
  {
    "href": "/nes/7430/",
    "src": "/media/images/2010124105445874.jpg"
  },
  {
    "href": "/nes/3283/",
    "src": "/media/images/20101611238349.jpg"
  },
  {
    "href": "/nes/7418/",
    "src": "/media/images/2010124105429426.jpg"
  },
  {
    "href": "/nes/2441/",
    "src": "/media/images/200810181246399934.gif"
  },
  {
    "href": "/nes/7393/",
    "src": "/media/images/2010124105413143.jpg"
  },
  {
    "href": "/nes/3308/",
    "src": "/media/images/2010161141362.jpg"
  },
  {
    "href": "/nes/3297/",
    "src": "/media/images/20101611317681.jpg"
  },
  {
    "href": "/nes/3294/",
    "src": "/media/images/2010161138130.jpg"
  },
  {
    "href": "/nes/3278/",
    "src": "/media/images/20101611223475.jpg"
  },
  {
    "href": "/nes/318/",
    "src": "/media/images/318.jpg"
  },
  {
    "href": "/nes/3309/",
    "src": "/media/images/2010161145669.jpg"
  },
  {
    "href": "/nes/7422/",
    "src": "/media/images/2010124105431778.jpg"
  },
  {
    "href": "/nes/7410/",
    "src": "/media/images/2010124105425835.jpg"
  },
  {
    "href": "/nes/7436/",
    "src": "/media/images/2010124105450758.jpg"
  },
  {
    "href": "/nes/7406/",
    "src": "/media/images/2010124105422238.jpg"
  },
  {
    "href": "/nes/7438/",
    "src": "/media/images/2010124105451315.jpg"
  },
  {
    "href": "/nes/7434/",
    "src": "/media/images/2010124105448457.jpg"
  },
  {
    "href": "/nes/7433/",
    "src": "/media/images/2010124105447503.jpg"
  },
  {
    "href": "/nes/7427/",
    "src": "/media/images/2010124105443463.jpg"
  },
  {
    "href": "/nes/7423/",
    "src": "/media/images/2010124105432398.jpg"
  },
  {
    "href": "/nes/7398/",
    "src": "/media/images/2010124105416177.jpg"
  },
  {
    "href": "/nes/7391/",
    "src": "/media/images/2010124105412867.jpg"
  },
  {
    "href": "/nes/7390/",
    "src": "/media/images/2010124105411576.jpg"
  },
  {
    "href": "/nes/7387/",
    "src": "/media/images/201012410548537.jpg"
  },
  {
    "href": "/nes/3305/",
    "src": "/media/images/20101611350549.jpg"
  },
  {
    "href": "/nes/3299/",
    "src": "/media/images/20101611329401.jpg"
  },
  {
    "href": "/nes/3298/",
    "src": "/media/images/20101611326613.jpg"
  },
  {
    "href": "/nes/3292/",
    "src": "/media/images/2010161132598.jpg"
  },
  {
    "href": "/nes/3291/",
    "src": "/media/images/20101611259678.jpg"
  },
  {
    "href": "/nes/3288/",
    "src": "/media/images/20101611250733.jpg"
  }
]